README.md
setup.py
plastic/__init__.py
plastic/column.py
plastic/connection.py
plastic/metaplastic.py
plastic/plastic.py
plastic/record.py
plastic/recordset.py
plastic.egg-info/PKG-INFO
plastic.egg-info/SOURCES.txt
plastic.egg-info/dependency_links.txt
plastic.egg-info/top_level.txt
plastic/connectors/__init__.py
plastic/connectors/_template.py
plastic/connectors/ignition.py
plastic/connectors/mysql.py
plastic/connectors/sqlite.py