Metadata-Version: 2.1
Name: plastic
Version: 0.2.0
Summary: An ORM interface that molds itself to your data.
Home-page: https://github.com/CorsoSource/plastic
Author: Andrew Geiger
Author-email: andrew.geiger@corsosystems.com
License: UNKNOWN
Platform: UNKNOWN
Classifier: Development Status :: 4 - Beta
Classifier: Programming Language :: Python :: 3
Classifier: License :: OSI Approved :: Apache Software License
Classifier: Operating System :: OS Independent
Requires-Python: >=3.6
